format_json/__init__.py
format_json/main.py
format_json-0.1.2.dist-info/METADATA
format_json-0.1.2.dist-info/WHEEL
format_json-0.1.2.dist-info/entry_points.txt
format_json-0.1.2.dist-info/licenses/LICENSE
format_json-0.1.2.dist-info/RECORD
