Metadata-Version: 2.4
Name: format-json
Version: 0.1.2
Summary: A CLI and pre-commit hook for formatting JSON with configurable trailing newline handling.
Project-URL: Homepage, https://github.com/jsh9/format-json
Project-URL: Repository, https://github.com/jsh9/format-json
Project-URL: Issues, https://github.com/jsh9/format-json/issues
Author: format-json maintainers
License: MIT License
License-File: LICENSE
Keywords: cli,formatter,json,pre-commit
Classifier: License :: OSI Approved :: MIT License
Classifier: Programming Language :: Python :: 3
Classifier: Programming Language :: Python :: 3 :: Only
Classifier: Programming Language :: Python :: 3.10
Classifier: Programming Language :: Python :: 3.11
Classifier: Programming Language :: Python :: 3.12
Classifier: Programming Language :: Python :: 3.13
Classifier: Topic :: Software Development :: Build Tools
Classifier: Topic :: Utilities
Requires-Python: >=3.10
Provides-Extra: dev
Requires-Dist: flake8-broken-line; extra == 'dev'
Requires-Dist: flake8-clean-block; extra == 'dev'
Requires-Dist: flake8-picky-parentheses; extra == 'dev'
Requires-Dist: muff; extra == 'dev'
Requires-Dist: mypy; extra == 'dev'
Requires-Dist: pre-commit; extra == 'dev'
Requires-Dist: pytest; extra == 'dev'
